maintainer/__init__.py
maintainer/nacos_maintainer_client.py
maintainer/ai/__init__.py
maintainer/ai/nacos_ai_maintainer_service.py
maintainer/ai/model/__init__.py
maintainer/ai/model/a2a.py
maintainer/common/__init__.py
maintainer/common/auth.py
maintainer/common/utils.py
maintainer/transport/__init__.py
maintainer/transport/auth_client.py
maintainer/transport/client_http_proxy.py
maintainer/transport/http_agent.py
nacos_maintainer_sdk_python-0.5.3.dist-info/licenses/LICENSE
nacos_maintainer_sdk_python-0.5.3.dist-info/METADATA
nacos_maintainer_sdk_python-0.5.3.dist-info/WHEEL
nacos_maintainer_sdk_python-0.5.3.dist-info/top_level.txt
nacos_maintainer_sdk_python-0.5.3.dist-info/RECORD
