Metadata-Version: 2.4
Name: nacos-maintainer-sdk-python
Version: 0.5.3
Summary: Nacos Maintainer Sdk for Python
Author: nacos
License: Apache License 2.0
Project-URL: Homepage, https://github.com/nacos-group/nacos-maintainer-sdk-python.git
Project-URL: Repository, https://github.com/nacos-group/nacos-maintainer-sdk-python.git
Classifier: Topic :: Software Development :: Libraries :: Python Modules
Classifier: Operating System :: OS Independent
Classifier: Programming Language :: Python
Classifier: Programming Language :: Python :: 3.10
Classifier: Programming Language :: Python :: 3.11
Classifier: Programming Language :: Python :: 3.12
Requires-Python: >=3.10
License-File: LICENSE
Requires-Dist: aiohttp>=3.8.6
Requires-Dist: pydantic>=2.5.3
Requires-Dist: nacos-sdk-python>=3.0.2
Dynamic: license-file
